hamal_utils/__init__.py
hamal_utils/code/__init__.py
hamal_utils/code/common.py
hamal_utils/code/version.py
hamal_utils/code/s3_utils/__init__.py
hamal_utils/code/s3_utils/s3_custom_client.py
hamal_utils/code/s3_utils/s3_custom_resource.py
hamal_utils/code/s3_utils/session.py
hamal_utils/code/utils/__init__.py
hamal_utils/code/utils/hash_util.py
hamal_utils-0.0.69.dist-info/METADATA
hamal_utils-0.0.69.dist-info/WHEEL
hamal_utils-0.0.69.dist-info/top_level.txt
hamal_utils-0.0.69.dist-info/RECORD
